[
  {
    "name": "Yann Sommer",
    "position": "GK",
    "number": 1,
    "age": 33,
    "club": "Borussia Mönchengladbach",
    "caps": 77,
    "goals": 0,
    "rating": 7.0,
    "preferred_foot": "R",
    "height_cm": 180,
    "wikipedia_url": "https://en.wikipedia.org/wiki/Yann_Sommer",
    "id": "8bf2118b08ef",
    "name_zh": "Yann Sommer",
    "photo_path": "/Users/shike/Desktop/code/wordcup-forecast/缓存/球员照片/8bf2118b08ef.jpg"
  },
  {
    "name": "Edimilson Fernandes",
    "position": "CB",
    "number": 2,
    "age": 26,
    "club": "Mainz 05",
    "caps": 22,
    "goals": 2,
    "rating": 7.0,
    "preferred_foot": "R",
    "height_cm": 180,
    "wikipedia_url": "https://en.wikipedia.org/wiki/Edimilson_Fernandes",
    "id": "c7e7463df10c",
    "name_zh": "Edimilson Fernandes"
  },
  {
    "name": "Silvan Widmer",
    "position": "CB",
    "number": 3,
    "age": 29,
    "club": "Mainz 05",
    "caps": 34,
    "goals": 2,
    "rating": 7.0,
    "preferred_foot": "R",
    "height_cm": 180,
    "wikipedia_url": "https://en.wikipedia.org/wiki/Silvan_Widmer",
    "id": "f0715f7b7bdc",
    "name_zh": "Silvan Widmer"
  },
  {
    "name": "Nico Elvedi",
    "position": "CB",
    "number": 4,
    "age": 26,
    "club": "Borussia Mönchengladbach",
    "caps": 41,
    "goals": 1,
    "rating": 7.0,
    "preferred_foot": "R",
    "height_cm": 180,
    "wikipedia_url": "https://en.wikipedia.org/wiki/Nico_Elvedi",
    "id": "487dc7a9ae29",
    "name_zh": "Nico Elvedi",
    "photo_path": "/Users/shike/Desktop/code/wordcup-forecast/缓存/球员照片/487dc7a9ae29.jpg"
  },
  {
    "name": "Manuel Akanji",
    "position": "CB",
    "number": 5,
    "age": 27,
    "club": "Manchester City",
    "caps": 43,
    "goals": 1,
    "rating": 7.0,
    "preferred_foot": "R",
    "height_cm": 180,
    "wikipedia_url": "https://en.wikipedia.org/wiki/Manuel_Akanji",
    "id": "1070e1455da5",
    "name_zh": "Manuel Akanji",
    "photo_path": "/Users/shike/Desktop/code/wordcup-forecast/缓存/球员照片/1070e1455da5.jpg"
  },
  {
    "name": "Denis Zakaria",
    "position": "CM",
    "number": 6,
    "age": 26,
    "club": "Chelsea",
    "caps": 43,
    "goals": 3,
    "rating": 7.0,
    "preferred_foot": "R",
    "height_cm": 180,
    "wikipedia_url": "https://en.wikipedia.org/wiki/Denis_Zakaria",
    "id": "5fd8ea7c4958",
    "name_zh": "Denis Zakaria",
    "photo_path": "/Users/shike/Desktop/code/wordcup-forecast/缓存/球员照片/5fd8ea7c4958.jpg"
  },
  {
    "name": "Breel Embolo",
    "position": "ST",
    "number": 7,
    "age": 25,
    "club": "Monaco",
    "caps": 59,
    "goals": 11,
    "rating": 7.0,
    "preferred_foot": "R",
    "height_cm": 180,
    "wikipedia_url": "https://en.wikipedia.org/wiki/Breel_Embolo",
    "id": "986a6542ac73",
    "name_zh": "Breel Embolo",
    "photo_path": "/Users/shike/Desktop/code/wordcup-forecast/缓存/球员照片/986a6542ac73.jpg"
  },
  {
    "name": "Remo Freuler",
    "position": "CM",
    "number": 8,
    "age": 30,
    "club": "Nottingham Forest",
    "caps": 49,
    "goals": 5,
    "rating": 7.0,
    "preferred_foot": "R",
    "height_cm": 180,
    "wikipedia_url": "https://en.wikipedia.org/wiki/Remo_Freuler",
    "id": "4c64c0193035",
    "name_zh": "Remo Freuler",
    "photo_path": "/Users/shike/Desktop/code/wordcup-forecast/缓存/球员照片/4c64c0193035.jpg"
  },
  {
    "name": "Haris Seferovic",
    "position": "ST",
    "number": 9,
    "age": 30,
    "club": "Galatasaray",
    "caps": 89,
    "goals": 25,
    "rating": 7.0,
    "preferred_foot": "R",
    "height_cm": 180,
    "wikipedia_url": "https://en.wikipedia.org/wiki/Haris_Seferovic",
    "id": "fd874325cad2",
    "name_zh": "Haris Seferovic",
    "photo_path": "/Users/shike/Desktop/code/wordcup-forecast/缓存/球员照片/fd874325cad2.jpg"
  },
  {
    "name": "Granit Xhaka",
    "position": "CM",
    "number": 10,
    "age": 30,
    "club": "Arsenal",
    "caps": 107,
    "goals": 12,
    "rating": 7.0,
    "preferred_foot": "R",
    "height_cm": 180,
    "wikipedia_url": "https://en.wikipedia.org/wiki/Granit_Xhaka",
    "id": "f8cd12a1012b",
    "name_zh": "Granit Xhaka",
    "photo_path": "/Users/shike/Desktop/code/wordcup-forecast/缓存/球员照片/f8cd12a1012b.jpg"
  },
  {
    "name": "Renato Steffen",
    "position": "CB",
    "number": 11,
    "age": 31,
    "club": "Lugano",
    "caps": 28,
    "goals": 1,
    "rating": 7.0,
    "preferred_foot": "R",
    "height_cm": 180,
    "wikipedia_url": "https://en.wikipedia.org/wiki/Renato_Steffen",
    "id": "7326d1347ee4",
    "name_zh": "Renato Steffen"
  },
  {
    "name": "Jonas Omlin",
    "position": "GK",
    "number": 12,
    "age": 28,
    "club": "Montpellier",
    "caps": 4,
    "goals": 0,
    "rating": 7.0,
    "preferred_foot": "R",
    "height_cm": 180,
    "wikipedia_url": "https://en.wikipedia.org/wiki/Jonas_Omlin",
    "id": "0660ce4fba84",
    "name_zh": "Jonas Omlin"
  },
  {
    "name": "Ricardo Rodriguez",
    "position": "CB",
    "number": 13,
    "age": 30,
    "club": "Torino",
    "caps": 100,
    "goals": 9,
    "rating": 7.0,
    "preferred_foot": "R",
    "height_cm": 180,
    "wikipedia_url": "https://en.wikipedia.org/wiki/Ricardo_Rodriguez_(footballer)",
    "id": "673368e8216e",
    "name_zh": "Ricardo Rodriguez"
  },
  {
    "name": "Michel Aebischer",
    "position": "CM",
    "number": 14,
    "age": 25,
    "club": "Bologna",
    "caps": 12,
    "goals": 0,
    "rating": 7.0,
    "preferred_foot": "R",
    "height_cm": 180,
    "wikipedia_url": "https://en.wikipedia.org/wiki/Michel_Aebischer",
    "id": "c591472f6c42",
    "name_zh": "Michel Aebischer"
  },
  {
    "name": "Djibril Sow",
    "position": "CM",
    "number": 15,
    "age": 25,
    "club": "Eintracht Frankfurt",
    "caps": 32,
    "goals": 0,
    "rating": 7.0,
    "preferred_foot": "R",
    "height_cm": 180,
    "wikipedia_url": "https://en.wikipedia.org/wiki/Djibril_Sow",
    "id": "65ea60f0fa1e",
    "name_zh": "Djibril Sow",
    "photo_path": "/Users/shike/Desktop/code/wordcup-forecast/缓存/球员照片/65ea60f0fa1e.jpg"
  },
  {
    "name": "Christian Fassnacht",
    "position": "CM",
    "number": 16,
    "age": 29,
    "club": "Young Boys",
    "caps": 16,
    "goals": 4,
    "rating": 7.0,
    "preferred_foot": "R",
    "height_cm": 180,
    "wikipedia_url": "https://en.wikipedia.org/wiki/Christian_Fassnacht",
    "id": "29212f861eda",
    "name_zh": "Christian Fassnacht",
    "photo_path": "/Users/shike/Desktop/code/wordcup-forecast/缓存/球员照片/29212f861eda.jpg"
  },
  {
    "name": "Ruben Vargas",
    "position": "ST",
    "number": 17,
    "age": 24,
    "club": "FC Augsburg",
    "caps": 27,
    "goals": 4,
    "rating": 7.0,
    "preferred_foot": "R",
    "height_cm": 180,
    "wikipedia_url": "https://en.wikipedia.org/wiki/Ruben_Vargas",
    "id": "8862933d3d23",
    "name_zh": "Ruben Vargas"
  },
  {
    "name": "Eray Cömert",
    "position": "CB",
    "number": 18,
    "age": 24,
    "club": "Valencia",
    "caps": 10,
    "goals": 0,
    "rating": 7.0,
    "preferred_foot": "R",
    "height_cm": 180,
    "wikipedia_url": "https://en.wikipedia.org/wiki/Eray_C%C3%B6mert",
    "id": "77fe5a779d66",
    "name_zh": "Eray Cömert"
  },
  {
    "name": "Noah Okafor",
    "position": "ST",
    "number": 19,
    "age": 22,
    "club": "Red Bull Salzburg",
    "caps": 9,
    "goals": 2,
    "rating": 7.0,
    "preferred_foot": "R",
    "height_cm": 180,
    "wikipedia_url": "https://en.wikipedia.org/wiki/Noah_Okafor",
    "id": "38b848671a92",
    "name_zh": "Noah Okafor",
    "photo_path": "/Users/shike/Desktop/code/wordcup-forecast/缓存/球员照片/38b848671a92.jpg"
  },
  {
    "name": "Fabian Frei",
    "position": "CM",
    "number": 20,
    "age": 33,
    "club": "Basel",
    "caps": 22,
    "goals": 3,
    "rating": 7.0,
    "preferred_foot": "R",
    "height_cm": 180,
    "wikipedia_url": "https://en.wikipedia.org/wiki/Fabian_Frei",
    "id": "f857fca2449a",
    "name_zh": "Fabian Frei"
  },
  {
    "name": "Gregor Kobel",
    "position": "GK",
    "number": 21,
    "age": 24,
    "club": "Borussia Dortmund",
    "caps": 3,
    "goals": 0,
    "rating": 7.0,
    "preferred_foot": "R",
    "height_cm": 180,
    "wikipedia_url": "https://en.wikipedia.org/wiki/Gregor_Kobel",
    "id": "2b870e5ae173",
    "name_zh": "Gregor Kobel"
  },
  {
    "name": "Fabian Schär",
    "position": "CB",
    "number": 22,
    "age": 30,
    "club": "Newcastle United",
    "caps": 73,
    "goals": 8,
    "rating": 7.0,
    "preferred_foot": "R",
    "height_cm": 180,
    "wikipedia_url": "https://en.wikipedia.org/wiki/Fabian_Sch%C3%A4r",
    "id": "43928cc7d8ee",
    "name_zh": "Fabian Schär",
    "photo_path": "/Users/shike/Desktop/code/wordcup-forecast/缓存/球员照片/43928cc7d8ee.jpg"
  },
  {
    "name": "Xherdan Shaqiri",
    "position": "CM",
    "number": 23,
    "age": 31,
    "club": "Chicago Fire FC",
    "caps": 109,
    "goals": 26,
    "rating": 7.0,
    "preferred_foot": "R",
    "height_cm": 180,
    "wikipedia_url": "https://en.wikipedia.org/wiki/Xherdan_Shaqiri",
    "id": "40b0db9ca837",
    "name_zh": "Xherdan Shaqiri",
    "photo_path": "/Users/shike/Desktop/code/wordcup-forecast/缓存/球员照片/40b0db9ca837.jpg"
  },
  {
    "name": "Philipp Köhn",
    "position": "GK",
    "number": 24,
    "age": 24,
    "club": "Red Bull Salzburg",
    "caps": 0,
    "goals": 0,
    "rating": 7.0,
    "preferred_foot": "R",
    "height_cm": 180,
    "wikipedia_url": "https://en.wikipedia.org/wiki/Philipp_K%C3%B6hn",
    "id": "8fb2ec9a73f4",
    "name_zh": "Philipp Köhn"
  },
  {
    "name": "Fabian Rieder",
    "position": "CM",
    "number": 25,
    "age": 20,
    "club": "Young Boys",
    "caps": 0,
    "goals": 0,
    "rating": 7.0,
    "preferred_foot": "R",
    "height_cm": 180,
    "wikipedia_url": "https://en.wikipedia.org/wiki/Fabian_Rieder",
    "id": "880d12955f99",
    "name_zh": "Fabian Rieder"
  },
  {
    "name": "Ardon Jashari",
    "position": "CM",
    "number": 26,
    "age": 20,
    "club": "Luzern",
    "caps": 1,
    "goals": 0,
    "rating": 7.0,
    "preferred_foot": "R",
    "height_cm": 180,
    "wikipedia_url": "https://en.wikipedia.org/wiki/Ardon_Jashari",
    "id": "e7254879888f",
    "name_zh": "Ardon Jashari"
  }
]
